{
    "AIOT2101": {
        "inherits": [
            "MCU_M480"
        ],
        "macros_add": [
            "MBEDTLS_CONFIG_HW_SUPPORT"
        ],
        "detect_code": [
            "1234"
        ],
        "device_name": "M484SIDAE",
        "device_has_remove": ["RTC"],
        "overrides": {
            "hxt-present": true,
            "lxt-present": false,
            "stdio-uart": "UART_1",
            "stdio-uart-tx": "PA_9",
            "stdio-uart-rx": "PA_8",
            "network-default-interface-type": "WIFI",
            "usb-device-hsusbd": 1
        }
    }
}
